Workbook

Sheet 總覽
A1: 30 天重建總覽
A2: 先保住資本，再談績效｜所有數字由各紀錄表自動彙總
A4: 核心指標
A5: 目前零下注連續天數 | C5: 每日完成率 | E5: 重訓次數 | G5: 平均衝動
A6: =IF(COUNTA('每日檢核'!$B$5:$B$34)=0,0,INDEX('每日檢核'!$J$5:$J$34,COUNTA('每日檢核'!$B$5:$B$34))) | C6: =COUNTIF('每日檢核'!$B$5:$B$34,"是")/30 | E6: =COUNTIF('每日檢核'!$G$5:$G$34,"是") | G6: =IFERROR(AVERAGE('每日檢核'!$D$5:$D$34),0)
A7: 總訓練組數 | C7: 總訓練量 | E7: 目前現金 | G7: 緩衝達成率
A8: =COUNTA('重訓紀錄'!$C$5:$C$304) | C8: =SUM('重訓紀錄'!$H$5:$H$304) | E8: ='資金控制'!B9 | G8: =MIN('資金控制'!B9/'資金控制'!B7,1)
A10: 今天只做三件事
A11: 1. 封閉資金入口：暫停運彩、終止 Tradeify、刪除 App、移除付款資料與取消盤口內容。
A12: 2. 建立資金防線：設定入薪後自動轉存 80,000 元，寫下『210 萬已結束，不靠下注追回』。
A13: 3. 建立晚間替代：完成第一次全身重訓，寫第一筆日誌，再散步或看一集影集。
A15: 本週檢查
A16: 項目 | B16: 目標 | C16: 目前 | D16: 狀態
A17: 零下注 | B17: 7 天 | C17: ='每週檢討'!D5 | D17: =IF(C17>=7,"達成","未達")
A18: 重訓 | B18: 3 次 | C18: ='每週檢討'!E5 | D18: =IF(C18>=3,"達成","未達")
A19: 散步 | B19: 120 分鐘 | C19: ='每週檢討'!F5 | D19: =IF(C19>=120,"達成","未達")
A20: 日誌 | B20: 7 天 | C20: =COUNTA('每日檢核'!$B$5:$B$11) | D20: =IF(C20>=7,"達成","未達")

Sheet 每日檢核
A1: 30 天每日檢核
A2: 2026-08-04 至 2026-09-02｜空白代表尚未回報，不會自動判定失敗
A4: 日期 | B4: 零下注 | C4: 查看盤口 | D4: 衝動 0–10 | E4: 觸發原因 | F4: 替代行動 | G4: 完成重訓 | H4: 散步分鐘 | I4: 睡眠小時 | J4: 連續零下注
A5: 46238 | B5: 是 | C5: 否 | D5: 0 | G5: =IF(COUNTIF('重訓紀錄'!$A$5:$A$304,A5)>0,"是",IF(B5="","","否")) | H5: 0 | I5: 8 | J5: =IF(B5="","",IF(B5="是",1,0))
A6: 46239 | B6: 是 | C6: 否 | D6: 0 | G6: 否 | H6: 30 | I6: 7.5 | J6: =IF(B6="","",IF(B6="是",J5+1,0))
A7: 46240 | B7: 是 | C7: 否 | D7: 0 | G7: 否 | H7: 30 | I7: 7 | J7: =IF(B7="是",J6+1,0)
A8: 46241 | B8: 是 | C8: 否 | D8: 1 | E8: 看到 DC 群組的運彩分享 | F8: 無 | G8: 否 | H8: 0 | I8: 8 | J8: =IF(B8="是",J7+1,0)
A9: 46242 | B9: 是 | C9: 否 | D9: 0 | G9: 是 | H9: 0 | I9: 10 | J9: =IF(B9="是",J8+1,0)
A10: 46243 | B10: 是 | C10: 否 | D10: 0 | G10: 否 | H10: 15 | I10: 9 | J10: =IF(B10="","",IF(B10="是",J9+1,0))
A11: 46244 | B11: 是 | C11: 否 | D11: 0 | G11: 否 | H11: 20 | I11: 3 | J11: =IF(B11="","",IF(B11="是",J10+1,0))
A12: 46245 | B12: 是 | C12: 否 | D12: 0 | G12: 是 | H12: 0 | I12: 9 | J12: =IF(B12="","",IF(B12="是",J11+1,0))
A13: 46246 | B13: 是 | C13: 否 | D13: 0 | G13: =IF(COUNTIF('重訓紀錄'!$A$5:$A$304,A13)>0,"是",IF(B13="","","否")) | H13: 0 | I13: 3 | J13: =IF(B13="","",IF(B13="是",J12+1,0))
A14: 46247 | B14: 是 | C14: 否 | D14: 0 | G14: 否 | H14: 10 | I14: 6 | J14: =IF(B14="","",IF(B14="是",J13+1,0))
A15: 46248 | B15: 是 | C15: 否 | D15: 0 | G15: =IF(COUNTIF('重訓紀錄'!$A$5:$A$304,A15)>0,"是",IF(B15="","","否")) | H15: 0 | I15: 8 | J15: =IF(B15="","",IF(B15="是",J14+1,0))
A16: 46249 | B16: 是 | C16: 否 | D16: 0 | G16: 否 | H16: 40 | I16: 8 | J16: =IF(B16="","",IF(B16="是",J15+1,0))
A17: 46250 | B17: 是 | C17: 否 | D17: 0 | G17: 否 | H17: 0 | I17: 11 | J17: =IF(B17="","",IF(B17="是",J16+1,0))
A18: 46251 | B18: 是 | C18: 否 | D18: 0 | G18: 否 | H18: 0 | I18: 8 | J18: =IF(B18="","",IF(B18="是",J17+1,0))
A19: 46252 | B19: 是 | C19: 否 | D19: 0 | G19: =IF(COUNTIF('重訓紀錄'!$A$5:$A$304,A19)>0,"是",IF(B19="","","否")) | H19: 30 | I19: 8 | J19: =IF(B19="","",IF(B19="是",J18+1,0))
A20: 46253 | B20: 是 | C20: 否 | D20: 0 | G20: 否 | H20: 0 | I20: 3 | J20: =IF(B20="","",IF(B20="是",J19+1,0))
A21: 46254 | B21: 是 | C21: 否 | D21: 0 | G21: 否 | H21: 30 | I21: 8 | J21: =IF(B21="","",IF(B21="是",J20+1,0))
A22: 46255 | B22: 是 | C22: 否 | D22: 0 | G22: 否 | H22: 0 | I22: 0 | J22: =IF(B22="","",IF(B22="是",J21+1,0))
A23: 46256 | B23: 是 | C23: 否 | D23: 0 | G23: 否 | H23: 0 | I23: 7 | J23: =IF(B23="","",IF(B23="是",J22+1,0))
A24: 46257 | B24: 是 | C24: 否 | D24: 0 | G24: 否 | H24: 0 | I24: 7 | J24: =IF(B24="","",IF(B24="是",J23+1,0))
A25: 46258 | G25: =IF(COUNTIF('重訓紀錄'!$A$5:$A$304,A25)>0,"是",IF(B25="","","否")) | J25: =IF(B25="","",IF(B25="是",J24+1,0))
A26: 46259 | G26: =IF(COUNTIF('重訓紀錄'!$A$5:$A$304,A26)>0,"是",IF(B26="","","否")) | I26: 6 | J26: =IF(B26="","",IF(B26="是",J25+1,0))
A27: 46260 | B27: 是 | C27: 否 | D27: 0 | G27: 否 | H27: 0 | J27: =IF(B27="","",IF(B27="是",J26+1,0))
A28: 46261 | G28: =IF(COUNTIF('重訓紀錄'!$A$5:$A$304,A28)>0,"是",IF(B28="","","否")) | J28: =IF(B28="","",IF(B28="是",J27+1,0))
A29: 46262 | B29: 是 | C29: 否 | D29: 0 | G29: =IF(COUNTIF('重訓紀錄'!$A$5:$A$304,A29)>0,"是",IF(B29="","","否")) | H29: 0 | I29: 2 | J29: =IF(B29="","",IF(B29="是",J28+1,0))
A30: 46263 | G30: 否 | H30: 0 | J30: =IF(B30="","",IF(B30="是",J29+1,0))
A31: 46264 | G31: 否 | H31: 30 | J31: =IF(B31="","",IF(B31="是",J30+1,0))
A32: 46265 | G32: 否 | H32: 0 | J32: =IF(B32="","",IF(B32="是",J31+1,0))
A33: 46266 | G33: 否 | H33: 0 | J33: =IF(B33="","",IF(B33="是",J32+1,0))
A34: 46267 | G34: 否 | H34: 0 | J34: =IF(B34="","",IF(B34="是",J33+1,0))
A36: 準備日基準（不納入 30 天統計）
A37: 日期 | B37: 零下注 | C37: 查看盤口 | D37: 衝動 0–10 | E37: 觸發原因 | F37: 替代行動 | G37: 完成重訓 | H37: 散步分鐘 | I37: 睡眠小時 | J37: 備註
A38: 46237 | B38: 是 | C38: 是 | D38: 3 | E38: 看到 DC 群通知與推薦 | F38: 將運彩下注上限改成 0 | G38: 否 | H38: 15 | I38: 6 | J38: 準備日；不計入正式 30 天完成率。
A39: 46276 | H39: 20

Sheet 重訓紀錄
A1: 逐組重訓紀錄
A2: 啞鈴填單手重量；自重動作重量填 0 並在備註註明「自重」
A4: 日期 | B4: 訓練名稱 | C4: 動作 | D4: 組次 | E4: 重量（kg） | F4: 次數 | G4: DBR | H4: 訓練量 | I4: 備註
A5: 46238 | B5: 重訓 | C5: 睾丸繩下拉 | D5: 1 | E5: 6.25 | F5: 13 | G5: 2 | H5: =IF(OR(E5="",F5=""),"",E5*F5) | I5: 器械刻度確認為 kg；原始重量 6.25 kg；動作名稱照使用者原文。
A6: 46238 | B6: 重訓 | C6: 睾丸繩下拉 | D6: 2 | E6: 6.25 | F6: 11 | G6: 1 | H6: =IF(OR(E6="",F6=""),"",E6*F6) | I6: 器械刻度確認為 kg；原始重量 6.25 kg；動作名稱照使用者原文。
A7: 46238 | B7: 重訓 | C7: 睾丸繩下拉 | D7: 3 | E7: 6.25 | F7: 8 | G7: 1 | H7: =IF(OR(E7="",F7=""),"",E7*F7) | I7: 器械刻度確認為 kg；原始重量 6.25 kg；動作名稱照使用者原文。
A8: 46238 | B8: 重訓 | C8: 睾丸繩下拉 | D8: 4 | E8: 6.25 | F8: 5 | G8: 1 | H8: =IF(OR(E8="",F8=""),"",E8*F8) | I8: 器械刻度確認為 kg；原始重量 6.25 kg；動作名稱照使用者原文。
A9: 46238 | B9: 重訓 | C9: 腿推舉 | D9: 1 | E9: 40 | F9: 16 | G9: 3 | H9: =IF(OR(E9="",F9=""),"",E9*F9) | I9: 器械雙刻度確認：原回報 80 為 lb，同一插銷位置對應機台標示 40 kg；原回報剩餘 3 下（RIR 3），換算 RPE 7。
A10: 46238 | B10: 重訓 | C10: 腿推舉 | D10: 2 | E10: 40 | F10: 18 | G10: 2 | H10: =IF(OR(E10="",F10=""),"",E10*F10) | I10: 器械雙刻度確認：原回報 80 為 lb，同一插銷位置對應機台標示 40 kg；原回報剩餘 2 下（RIR 2），換算 RPE 8。
A11: 46238 | B11: 重訓 | C11: 腿推舉 | D11: 3 | E11: 40 | F11: 16 | G11: 1 | H11: =IF(OR(E11="",F11=""),"",E11*F11) | I11: 器械雙刻度確認：原回報 80 為 lb，同一插銷位置對應機台標示 40 kg；原回報剩餘 1 下（RIR 1），換算 RPE 9。
A12: 46238 | B12: 重訓 | C12: 腿推舉 | D12: 4 | E12: 40 | F12: 16 | G12: 0 | H12: =IF(OR(E12="",F12=""),"",E12*F12) | I12: 器械雙刻度確認：原回報 80 為 lb，同一插銷位置對應機台標示 40 kg；原回報剩餘 0 下（RIR 0），換算 RPE 10。
A13: 46238 | B13: 重訓 | C13: 蝴蝶機夾胸 | D13: 1 | E13: 25 | F13: 14 | G13: 0 | H13: =IF(OR(E13="",F13=""),"",E13*F13) | I13: 依照片辨識為坐姿胸推；原填 RPE 0 已更正為 RPE 10。
A14: 46238 | B14: 重訓 | C14: 蝴蝶機夾胸 | D14: 2 | E14: 25 | F14: 9 | G14: 0 | H14: =IF(OR(E14="",F14=""),"",E14*F14) | I14: 依照片辨識為坐姿胸推；原填 RPE 0 已更正為 RPE 10。
A15: 46238 | B15: 重訓 | C15: 蝴蝶機夾胸 | D15: 3 | E15: 20 | F15: 13 | G15: 0 | H15: =IF(OR(E15="",F15=""),"",E15*F15) | I15: 依照片辨識為坐姿胸推；原填 RPE 0 已更正為 RPE 10。
A16: 46238 | B16: 重訓 | C16: 蝴蝶機夾胸 | D16: 4 | E16: 20 | F16: 10 | G16: 0 | H16: =IF(OR(E16="",F16=""),"",E16*F16) | I16: 依照片辨識為坐姿胸推；原填 RPE 0 已更正為 RPE 10。
A17: 46238 | B17: 重訓 | C17: 腿後勾 | D17: 1 | E17: 32 | F17: 15 | G17: 5 | H17: =IF(OR(E17="",F17=""),"",E17*F17) | I17: 使用者確認為標準 RPE 5。
A18: 46238 | B18: 重訓 | C18: 腿後勾 | D18: 2 | E18: 40 | F18: 15 | G18: 1 | H18: =IF(OR(E18="",F18=""),"",E18*F18)
A19: 46238 | B19: 重訓 | C19: 腿後勾 | D19: 3 | E19: 40 | F19: 15 | G19: 0 | H19: =IF(OR(E19="",F19=""),"",E19*F19)
A20: 46238 | B20: 重訓 | C20: 腿後勾 | D20: 4 | E20: 40 | F20: 17 | G20: 0 | H20: =IF(OR(E20="",F20=""),"",E20*F20) | I20: 原填 RPE 0，使用者更正為 RPE 10。
A21: 46238 | B21: 重訓 | C21: 腿後勾 | D21: 5 | E21: 32 | F21: 20 | G21: 0 | H21: =IF(OR(E21="",F21=""),"",E21*F21)
A22: 46242 | B22: 重訓 | C22: 上斜胸推 | D22: 1 | E22: 25 | F22: 15 | G22: 2 | H22: =E22*F22
A23: 46242 | B23: 重訓 | C23: 上斜胸推 | D23: 2 | E23: 25 | F23: 14 | G23: 0 | H23: =E23*F23
A24: 46242 | B24: 重訓 | C24: 上斜胸推 | D24: 3 | E24: 25 | F24: 10 | G24: 0 | H24: =E24*F24
A25: 46242 | B25: 重訓 | C25: 上斜胸推 | D25: 4 | E25: 20 | F25: 10 | G25: 0 | H25: =E25*F25
A26: 46242 | B26: 重訓 | C26: 臀推機 | D26: 1 | E26: 20 | F26: 13 | G26: 6 | H26: =E26*F26
A27: 46242 | B27: 重訓 | C27: 臀推機 | D27: 2 | E27: 20 | F27: 15 | G27: 2 | H27: =E27*F27
A28: 46242 | B28: 重訓 | C28: 臀推機 | D28: 3 | E28: 20 | F28: 15 | G28: 2 | H28: =E28*F28
A29: 46242 | B29: 重訓 | C29: 臀推機 | D29: 4 | E29: 20 | F29: 15 | G29: 1 | H29: =E29*F29
A30: 46242 | B30: 重訓 | C30: 滑輪下拉 | D30: 1 | E30: 37.5 | F30: 15 | G30: 3 | H30: =E30*F30
A31: 46242 | B31: 重訓 | C31: 滑輪下拉 | D31: 2 | E31: 37.5 | F31: 12 | G31: 0 | H31: =E31*F31
A32: 46242 | B32: 重訓 | C32: 滑輪下拉 | D32: 3 | E32: 30 | F32: 16 | G32: 2 | H32: =E32*F32
A33: 46242 | B33: 重訓 | C33: 滑輪下拉 | D33: 4 | E33: 30 | F33: 14 | G33: 1 | H33: =E33*F33
... A37: 46242 | B37: 重訓 | C37: 腿外展 | D37: 2 | E37: 52.5 | F37: 13 | G37: 2 | H37: =E37*F37
A38: 46245 | B38: 重訓 | C38: 羅馬尼亞蹲 | D38: 1 | E38: 0 | F38: 13 | G38: 5 | H38: =IF(OR(E38="",F38=""),"",E38*F38) | I38: 自重；使用者回報 DBR 5，未視為 RPE。
A39: 46245 | B39: 重訓 | C39: 羅馬尼亞蹲 | D39: 2 | E39: 0 | F39: 15 | G39: 3 | H39: =IF(OR(E39="",F39=""),"",E39*F39) | I39: 自重；使用者回報 DBR 3，未視為 RPE。
A40: 46245 | B40: 重訓 | C40: 羅馬尼亞蹲 | D40: 3 | E40: 5 | F40: 13 | G40: 2 | H40: =IF(OR(E40="",F40=""),"",E40*F40) | I40: 額外加重 5 kg；使用者回報 DBR 2，未視為 RPE。
A41: 46245 | B41: 重訓 | C41: 羅馬尼亞蹲 | D41: 4 | E41: 5 | F41: 14 | G41: 2 | H41: =IF(OR(E41="",F41=""),"",E41*F41) | I41: 額外加重 5 kg；使用者回報 DBR 2，未視為 RPE。
A42: 46245 | B42: 重訓 | C42: 划船 | D42: 1 | E42: 22.5 | F42: 15 | G42: 5 | H42: =IF(OR(E42="",F42=""),"",E42*F42) | I42: DBR 5
A43: 46245 | B43: 重訓 | C43: 划船 | D43: 2 | E43: 30 | F43: 13 | G43: 5 | H43: =IF(OR(E43="",F43=""),"",E43*F43) | I43: DBR 5
A44: 46245 | B44: 重訓 | C44: 划船 | D44: 3 | E44: 30 | F44: 16 | G44: 2 | H44: =IF(OR(E44="",F44=""),"",E44*F44) | I44: DBR 2
A45: 46245 | B45: 重訓 | C45: 划船 | D45: 4 | E45: 30 | F45: 13 | G45: 1 | H45: =IF(OR(E45="",F45=""),"",E45*F45) | I45: DBR 1
A46: 46245 | B46: 重訓 | C46: 划船 | D46: 5 | E46: 30 | F46: 11 | G46: 0 | H46: =IF(OR(E46="",F46=""),"",E46*F46) | I46: DBR 0
A47: 46245 | B47: 重訓 | C47: 臀推機 | D47: 1 | E47: 20 | F47: 15 | G47: 5 | H47: =IF(OR(E47="",F47=""),"",E47*F47) | I47: DBR 5
A48: 46245 | B48: 重訓 | C48: 臀推機 | D48: 2 | E48: 20 | F48: 20 | G48: 3 | H48: =IF(OR(E48="",F48=""),"",E48*F48) | I48: DBR 3
A49: 46245 | B49: 重訓 | C49: 臀推機 | D49: 3 | E49: 20 | F49: 16 | G49: 2 | H49: =IF(OR(E49="",F49=""),"",E49*F49) | I49: DBR 2
... A203: 46276 | B203: 重訓 | C203: 腿內收 | D203: 4 | E203: 37.5 | F203: 13 | G203: 0 | H203: =IF(OR(E203="",F203=""),"",E203*F203) | I203: 重量未重複提供，沿用上一組 37.5 kg。
H204: =IF(OR(E204="",F204=""),"",E204*F204)
H205: =IF(OR(E205="",F205=""),"",E205*F205)
H206: =IF(OR(E206="",F206=""),"",E206*F206)
H207: =IF(OR(E207="",F207=""),"",E207*F207)
H208: =IF(OR(E208="",F208=""),"",E208*F208)
H209: =IF(OR(E209="",F209=""),"",E209*F209)
H210: =IF(OR(E210="",F210=""),"",E210*F210)
H211: =IF(OR(E211="",F211=""),"",E211*F211)
H212: =IF(OR(E212="",F212=""),"",E212*F212)
H213: =IF(OR(E213="",F213=""),"",E213*F213)
H214: =IF(OR(E214="",F214=""),"",E214*F214)
H215: =IF(OR(E215="",F215=""),"",E215*F215)
... H304: =IF(OR(E304="",F304=""),"",E304*F304)

Sheet 資金控制
A1: 資金控制
A2: 只記總額，不保存銀行帳號、信用卡號或登入資訊
A4: 基準項目 | B4: 金額（TWD）
A5: 起始現金 | B5: 20000
A6: 投資資產（基準） | B6: 1030000
A7: 現金緩衝目標 | B7: 121200
A8: 入薪轉存目標 | B8: 80000
A9: 目前現金 | B9: =B5+SUM(B14:B25)
A10: 距離目標 | B10: =B7-B9
A12: 轉存紀錄
A13: 日期 | B13: 金額（TWD） | C13: 備註
A14: 46239 | B14: 50000 | C14: 薪資入帳 133,735 元；轉入現金緩衝
A27: 每週資產核對
A28: 核對日 | B28: 現金 | C28: 投資資產 | D28: 負債 | E28: 備註
A29: 46243
A30: 46250
A31: 46257
A32: 46264
A33: 46267
A35: 資料來源：使用者於 2026-08-03 對話提供。210 萬歷史損失不列為待追回資產；本表只追蹤未來資金控制。

Sheet 每週檢討
A1: 每週檢討
A2: 第 4 週涵蓋最後 9 天；黃色欄位由你自行填寫
A4: 週期 | B4: 開始日 | C4: 結束日 | D4: 零下注天數 | E4: 重訓次數 | F4: 散步分鐘 | G4: 平均衝動 | H4: 違規次數 | I4: 本週最強觸發 | J4: 有效替代方法 | K4: 下週修正
A5: 第 1 週 | B5: 46238 | C5: 46244 | D5: =COUNTIFS('每日檢核'!$A$5:$A$34,">="&B5,'每日檢核'!$A$5:$A$34,"<="&C5,'每日檢核'!$B$5:$B$34,"是") | E5: =COUNTIFS('每日檢核'!$A$5:$A$34,">="&B5,'每日檢核'!$A$5:$A$34,"<="&C5,'每日檢核'!$G$5:$G$34,"是") | F5: =SUMIFS('每日檢核'!$H$5:$H$34,'每日檢核'!$A$5:$A$34,">="&B5,'每日檢核'!$A$5:$A$34,"<="&C5) | G5: =IFERROR(AVERAGEIFS('每日檢核'!$D$5:$D$34,'每日檢核'!$A$5:$A$34,">="&B5,'每日檢核'!$A$5:$A$34,"<="&C5),0) | H5: =COUNTIFS('每日檢核'!$A$5:$A$34,">="&B5,'每日檢核'!$A$5:$A$34,"<="&C5,'每日檢核'!$B$5:$B$34,"否")+COUNTIFS('每日檢核'!$A$5:$A$34,">="&B5,'每日檢核'!$A$5:$A$34,"<="&C5,'每日檢核'!$C$5:$C$34,"是")
A6: 第 2 週 | B6: 46245 | C6: 46251 | D6: =COUNTIFS('每日檢核'!$A$5:$A$34,">="&B6,'每日檢核'!$A$5:$A$34,"<="&C6,'每日檢核'!$B$5:$B$34,"是") | E6: =COUNTIFS('每日檢核'!$A$5:$A$34,">="&B6,'每日檢核'!$A$5:$A$34,"<="&C6,'每日檢核'!$G$5:$G$34,"是") | F6: =SUMIFS('每日檢核'!$H$5:$H$34,'每日檢核'!$A$5:$A$34,">="&B6,'每日檢核'!$A$5:$A$34,"<="&C6) | G6: =IFERROR(AVERAGEIFS('每日檢核'!$D$5:$D$34,'每日檢核'!$A$5:$A$34,">="&B6,'每日檢核'!$A$5:$A$34,"<="&C6),0) | H6: =COUNTIFS('每日檢核'!$A$5:$A$34,">="&B6,'每日檢核'!$A$5:$A$34,"<="&C6,'每日檢核'!$B$5:$B$34,"否")+COUNTIFS('每日檢核'!$A$5:$A$34,">="&B6,'每日檢核'!$A$5:$A$34,"<="&C6,'每日檢核'!$C$5:$C$34,"是")
A7: 第 3 週 | B7: 46252 | C7: 46258 | D7: =COUNTIFS('每日檢核'!$A$5:$A$34,">="&B7,'每日檢核'!$A$5:$A$34,"<="&C7,'每日檢核'!$B$5:$B$34,"是") | E7: =COUNTIFS('每日檢核'!$A$5:$A$34,">="&B7,'每日檢核'!$A$5:$A$34,"<="&C7,'每日檢核'!$G$5:$G$34,"是") | F7: =SUMIFS('每日檢核'!$H$5:$H$34,'每日檢核'!$A$5:$A$34,">="&B7,'每日檢核'!$A$5:$A$34,"<="&C7) | G7: =IFERROR(AVERAGEIFS('每日檢核'!$D$5:$D$34,'每日檢核'!$A$5:$A$34,">="&B7,'每日檢核'!$A$5:$A$34,"<="&C7),0) | H7: =COUNTIFS('每日檢核'!$A$5:$A$34,">="&B7,'每日檢核'!$A$5:$A$34,"<="&C7,'每日檢核'!$B$5:$B$34,"否")+COUNTIFS('每日檢核'!$A$5:$A$34,">="&B7,'每日檢核'!$A$5:$A$34,"<="&C7,'每日檢核'!$C$5:$C$34,"是")
A8: 第 4 週 | B8: 46259 | C8: 46267 | D8: =COUNTIFS('每日檢核'!$A$5:$A$34,">="&B8,'每日檢核'!$A$5:$A$34,"<="&C8,'每日檢核'!$B$5:$B$34,"是") | E8: =COUNTIFS('每日檢核'!$A$5:$A$34,">="&B8,'每日檢核'!$A$5:$A$34,"<="&C8,'每日檢核'!$G$5:$G$34,"是") | F8: =SUMIFS('每日檢核'!$H$5:$H$34,'每日檢核'!$A$5:$A$34,">="&B8,'每日檢核'!$A$5:$A$34,"<="&C8) | G8: =IFERROR(AVERAGEIFS('每日檢核'!$D$5:$D$34,'每日檢核'!$A$5:$A$34,">="&B8,'每日檢核'!$A$5:$A$34,"<="&C8),0) | H8: =COUNTIFS('每日檢核'!$A$5:$A$34,">="&B8,'每日檢核'!$A$5:$A$34,"<="&C8,'每日檢核'!$B$5:$B$34,"否")+COUNTIFS('每日檢核'!$A$5:$A$34,">="&B8,'每日檢核'!$A$5:$A$34,"<="&C8,'每日檢核'!$C$5:$C$34,"是")

Sheet 規則與身份
A1: 規則與身份
A2: 這一頁不是勵志語錄；它是復發時必須照做的決策邊界
A4: 身份重建
A5: 舊身份 | B5: 我夠聰明，可以私下把損失贏回來；只要還有翻本機會，就不必承認失控。
A6: 五年反願景 | B6: 40 歲仍靠下注取得刺激、資產停滯並繼續隱瞞損失，睡前問自己：我到底在幹嘛？
A7: 新身份 | B7: 我是用可驗證行為保護資本的人；刺激不能碰我的資產。
A8: 30 天唯一目標 | B8: 連續 30 天不以真錢滿足翻本衝動，重新取得對資金與晚間生活的控制。
A10: 不可談判規則
A11: 1. 運彩、期貨實盤、prop firm 帳號、充值與替代帳戶交易全部為零。
A12: 2. 不主動查看盤口、預測推文、交易直播或請 AI 分析勝率。
A13: 3. 210 萬是已結束的代價，不設定追回期限。
A14: 4. 入薪後轉存 80,000 元；現金緩衝先達到 121,200 元。
A15: 5. 任何一次下注都算違規，不追損、不重寫規則，剩餘天數仍繼續執行。
A17: 明日三件事
A18: 1. 封閉資金入口：暫停運彩、終止 Tradeify、刪除 App、移除付款資料與取消盤口內容。
A19: 2. 建立資金防線：設定入薪後自動轉存 80,000 元，寫下『210 萬已結束，不靠下注追回』。
A20: 3. 建立晚間替代：完成第一次全身重訓，寫第一筆日誌，再散步或看一集影集。
A22: 違規處理與求助
A23: 立即停止，不追損；記錄金額、觸發點與使用管道。
... A26: 官方節制投注資料：https://article.sportslottery.com.tw/zh-tw/declaration/98?iframe

Sheet 飲食紀錄
A1: 飲食紀錄
A2: 只記實際吃的內容；未提供份量、飽足感或熱量時保持空白，不自行猜測
A4: 日期 | B4: 餐別 | C4: 餐廳／來源 | D4: 餐點內容 | E4: 蛋白質（g） | F4: 熱量（kcal） | G4: 備註 | H4: 碳水（g）
A5: 46237 | B5: 早餐 | D5: 培根蛋吐司、雞塊 | E5: 30 | F5: 750 | G5: 估算：早餐店培根蛋吐司＋一份雞塊；實際份量未提供。 碳水估算：吐司與雞塊裹粉合計約 65 g。 | H5: 65
A6: 46237 | B6: 午餐 | D6: 未進食 | E6: 0 | F6: 0 | H6: 0
A7: 46237 | B7: 晚餐 | C7: 樂晴牛排館 | D7: 牛排、雞排、酥皮濃湯 | E7: 95 | F7: 1450 | G7: 估算：樂晴牛排館雙排餐＋酥皮濃湯；依常見份量計。 碳水估算：主要來自酥皮濃湯，未另計醬料。 | H7: 45
A8: 46238 | B8: 早餐 | C8: 7-ELEVEN（711） | D8: 地瓜、海鹽水煮蛋、雞胸肉 | E8: 33 | F8: 300 | G8: 估算：7-ELEVEN 地瓜＋水煮蛋＋雞胸；實際品項份量未提供。 碳水估算：主要來自地瓜。 | H8: 35
A9: 46238 | B9: 午餐 | C9: 麥當勞 | D9: 大麥克、無糖可樂、小杯玉米湯、中薯 | E9: 30 | F9: 1042 | G9: 麥當勞營養資料估算：大麥克、中薯、小杯玉米湯、無糖可樂。 碳水估算：大麥克、中薯與小杯玉米湯合計約 120 g。 | H9: 120
A10: 46238 | B10: 晚餐 | D10: 雙倍雞肉飯，飯一半 | E10: 65 | F10: 850 | G10: 使用者回報：850 kcal、蛋白質 65 g。 碳水估算：主要來自半份白飯。 | H10: 55
A11: 46239 | B11: 早餐 | C11: 7-ELEVEN（711） | D11: 御選肉鬆飯糰、雙蔬鮪魚飯糰 | E11: 10.7 | F11: 485 | G11: 包裝營養標示合計：251＋234 kcal；蛋白質 5.5＋5.2 g。 碳水估算：兩顆飯糰合計約 90 g。 | H11: 90
A12: 46239 | B12: 午餐 | D12: 未進食 | E12: 0 | F12: 0 | H12: 0
A13: 46239 | B13: 晚餐 | C13: 鐵板燒 | D13: 松阪豬、嫩煎豆腐、豆芽菜、高麗菜、豆漿 | E13: 51 | F13: 714 | G13: 估算：鐵板燒松阪豬、豆腐、兩樣蔬菜與一瓶豆漿；豆漿採 144 kcal。 碳水估算：主要來自豆漿與蔬菜，未另計醬汁。 | H13: 28
A14: 46240 | B14: 早餐 | C14: 全家便利商店 | D14: 豆漿、地瓜、雞胸肉 | E14: 40 | F14: 394 | G14: 估算：全家豆漿、地瓜、雞胸；豆漿採使用者提供的 144 kcal。 碳水估算：地瓜約 35 g、豆漿約 13 g。 | H14: 48
A15: 46240 | B15: 午餐 | D15: 乳清蛋白粉 40g | E15: 30 | F15: 160 | G15: 估算：未提供品牌營養標示，按乳清粉 40g 約含蛋白質 30g、160 kcal 計。 碳水估算：未提供品牌，按一般乳清粉估算。 | H15: 4
A16: 46240 | B16: 晚餐 | D16: 炸雞排、炸杏鮑菇、炸魷魚 | E16: 54 | F16: 1054 | G16: 估算：炸雞排 630、炸杏鮑菇 174、炸魷魚 250 kcal；實際份量與裹粉用油不同會有差異。 碳水估算：主要來自裹粉。 | H16: 70
A17: 46241 | B17: 早餐 | D17: 地瓜、雞胸肉 | E17: 27 | F17: 250 | G17: 估算：依固定設定；地瓜 2g 蛋白質、雞胸肉 25g 蛋白質。 碳水估算：主要來自地瓜。 | H17: 35
A18: 46241 | B18: 午餐 | D18: 乳清蛋白粉 40g | E18: 30 | F18: 160 | G18: 估算：未提供品牌營養標示，按乳清粉 40g 約含蛋白質 30g、160 kcal 計。 碳水估算：未提供品牌，按一般乳清粉估算。 | H18: 4
A19: 46241 | B19: 晚餐 | C19: 火鍋 | D19: 肉片約 15 片、蔬菜 | E19: 45 | F19: 650 | G19: 估算：未提供肉種與重量，按一般火鍋肉片約 225g 加蔬菜計。 碳水估算：主要來自蔬菜與湯底，未另計醬料。 | H19: 15
A20: 46242 | B20: 早餐 | D20: 地瓜、雞胸肉 | E20: 32 | F20: 285 | G20: 雞胸肉蛋白質採使用者回報 30g；地瓜沿用 2g。熱量按一般份量估算。 碳水估算：主要來自地瓜。 | H20: 35
A21: 46242 | B21: 午餐 | D21: 乳清蛋白粉 60g、豆漿 | E21: 58 | F21: 384 | G21: 乳清按 60g 粉估算蛋白質 45g、240 kcal；豆漿沿用 13g、144 kcal。 碳水估算：乳清約 6 g、豆漿約 13 g。 | H21: 19
A22: 46242 | B22: 晚餐 | C22: 好食多涮涮鍋 | D22: 昆布鍋、12 盎司增肌減脂肉片、活鮑魚 3 個、白飯 1 碗 | E22: 82 | F22: 850 | G22: 估算：12 盎司約 340g。肉種與醬料未提供；依低脂火鍋肉片、鮑魚與白飯估算，未另計菜盤。 碳水估算：白飯約 60 g，加菜盤與湯底約 10 g。 | H22: 70
A105: 46242 | B105: 晚餐 | D105: 40g 乳清 + 1 杯豆漿 | E105: 43 | F105: 304 | G105: 晚餐後；未提供乳清品牌/營養標示與豆漿品牌/容量，蛋白質與熱量待補。 估算：沿用既有假設，40 g 乳清約蛋白質 30 g、160 kcal、碳水 4 g；豆漿約蛋白質 13 g、144 kcal、碳水 13 g。 | H105: 17
A106: 46243 | B106: 早餐 | C106: 7-ELEVEN（溏心蛋） | D106: 地瓜 + 7-ELEVEN 溏心蛋 2 顆 + 雞胸肉 | E106: 42.8 | F106: 391 | G106: 估算：地瓜與雞胸肉沿用 2026-08-08 早餐設定（蛋白質 32 g、熱量 285 kcal、碳水 35 g）；7-ELEVEN 溏心蛋每顆以蛋白質 5.4 g、熱量 53 kcal、碳水 1.4 g 估算。 | H106: 37.8
A107: 46243 | B107: 晚餐 | D107: 雞排 + 鰻魚 + 豆干 + 空心菜 + 豆腐 + 滷蛋 1 顆 + 素肚 | E107: 95 | F107: 1250 | G107: 依照片估算：一份炸雞排、鰻魚、豆干、空心菜、豆腐、滷蛋與素肚；實際份量、醬汁與用油未提供，營養數值為整盤估算。 蛋白質依使用者確認改採較保守估算 95 g。 | H107: 55
A108: 46243 | B108: 午餐 | C108: 使用者回報 | D108: 未進食 | G108: 使用者明確回報午餐未進食。
A109: 46244 | B109: 早餐 | D109: 地瓜 | E109: 2 | F109: 125 | G109: 估算：沿用先前地瓜固定設定，約蛋白質 2 g、碳水 35 g、125 kcal。 | H109: 35
A110: 46244 | B110: 午餐 | D110: 豆漿 + 乳清蛋白粉 60g | E110: 58 | F110: 384 | G110: 估算：沿用 2026-08-08 相同組合設定；乳清 60 g 約蛋白質 45 g、240 kcal、碳水 6 g；豆漿約蛋白質 13 g、144 kcal、碳水 13 g。 | H110: 19
A111: 46244 | B111: 晚餐 | D111: 牛肉飯 特大碗（飯一半） + 乳清蛋白粉 60g + 豆漿 | E111: 93 | F111: 1184 | G111: 估算：牛肉飯為特大碗但白飯實際吃約一半，先估蛋白質 35 g、碳水 60 g、800 kcal；乳清 60 g + 豆漿沿用既有設定，約蛋白質 58 g、碳水 19 g、384 kcal。合計約蛋白質 93 g、碳水 79 g、1184 kcal；店家、實際牛肉量與乳清/豆漿品牌未提供。 | H111: 79
A112: 46245 | B112: 早餐 | D112: 豆漿 + 乳清蛋白粉 40g + 地瓜 | E112: 45 | F112: 429 | G112: 估算：沿用既有設定；乳清蛋白粉 40 g 約蛋白質 30 g、碳水 4 g、160 kcal；豆漿約蛋白質 13 g、碳水 13 g、144 kcal；地瓜約蛋白質 2 g、碳水 35 g、125 kcal。合計約蛋白質 45 g、碳水 52 g、429 kcal；品牌與實際份量未提供。 | H112: 52
A113: 46245 | B113: 晚餐 | D113: 運動前：豆漿 + 乳清蛋白粉 40g | E113: 43 | F113: 304 | G113: 估算沿用既有設定：乳清蛋白粉 40g 約蛋白質 30g、碳水 4g、160 kcal；豆漿約蛋白質 13g、碳水 13g、144 kcal。 | H113: 17
A114: 46245 | B114: 晚餐 | D114: 雙倍雞肉飯 | E114: 65 | F114: 1050 | G114: 估算：沿用先前雙倍雞肉飯的雞肉份量設定，這次未註明飯減半，因此按完整一份白飯估算；約蛋白質 65 g、碳水 95 g、1050 kcal。實際醬汁與用油可能造成誤差。 | H114: 95
A115: 46245 | B115: 午餐 | C115: 使用者回報 | D115: 未進食 | G115: 使用者明確回報午餐未進食。
A116: 46246 | B116: 早餐 | C116: 使用者回報 | D116: 地瓜 + 豆漿 + 乳清蛋白粉 40g | E116: 45 | F116: 429 | G116: 估算沿用既有設定：乳清蛋白粉 40g 約蛋白質 30g、碳水 4g、160 kcal；豆漿約蛋白質 13g、碳水 13g、144 kcal；地瓜約蛋白質 2g、碳水 35g、125 kcal。 | H116: 52
A117: 46246 | B117: 午餐 | C117: 使用者回報 | D117: 黑咖啡 1 杯 | E117: 0 | F117: 0 | G117: 按無糖、無奶黑咖啡記錄；熱量視為可忽略。 | H117: 0
A118: 46246 | B118: 晚餐 | C118: 公開資料估算（FatSecret；商品版本可能不同） | D118: 全家 健身G肉餐盒 | E118: 29 | F118: 500 | G118: 採公開完整營養資料：每份約蛋白質 29 g、碳水 67.7 g、500 kcal。另有近期商品分享標示 385 g／481 kcal，推測版本或配方不同，因此本筆為透明估算。 | H118: 67.7
A119: 46246 | B119: 晚餐 | C119: 估算 | D119: 乳清蛋白粉 40g | E119: 32 | F119: 160 | G119: 未提供品牌與營養標示；以一般乳清蛋白粉約每 40 g 含蛋白質 32 g、碳水 4 g、160 kcal 估算。 | H119: 4
A120: 46246 | B120: 晚餐 | C120: 使用者回報 | D120: 豆漿 | G120: 品牌、容量與營養標示未提供；依規則不猜份量，蛋白質、碳水與熱量暫留空白待補。
A121: 46247 | B121: 早餐 | C121: 使用者回報 | D121: 豆漿 + 乳清蛋白粉 40g + 雞胸肉 + 地瓜 | E121: 75 | F121: 589 | G121: 估算沿用既有設定：豆漿約蛋白質 13g、碳水 13g、144 kcal；乳清蛋白粉 40g 約蛋白質 30g、碳水 4g、160 kcal；雞胸肉依使用者回報蛋白質 30g，沿用既有份量估算約 160 kcal；地瓜約蛋白質 2g、碳水 35g、125 kcal。 | H121: 52
A122: 46247 | B122: 晚餐 | C122: 使用者回報 | D122: 牛腩咖哩 + 雞腿肉 1 份 + 番茄 + 豆漿 + 乳清蛋白粉 40g | E122: 114 | F122: 1549 | G122: 修正估算：使用者補充白飯份量可能接近兩份且份量偏多。原估算上額外加約 1 碗白飯（蛋白質約 5g、碳水約 60g、280 kcal）。其餘牛腩咖哩、雞腿肉、番茄、豆漿與乳清沿用先前估算。 | H122: 157
A123: 46247 | B123: 午餐 | C123: 使用者回報 | D123: 未進食 | G123: 使用者明確回報午餐未進食。
A124: 46248 | B124: 早餐 | C124: 使用者回報 | D124: 雞胸肉 + 乳清蛋白粉 40g + 豆漿 + 地瓜 | E124: 75 | F124: 589 | G124: 估算沿用既有設定：雞胸肉依使用者回報蛋白質 30g，約 160 kcal；乳清蛋白粉 40g 約蛋白質 30g、碳水 4g、160 kcal；豆漿約蛋白質 13g、碳水 13g、144 kcal；地瓜約蛋白質 2g、碳水 35g、125 kcal。 | H124: 52
A125: 46248 | B125: 運動前 | C125: 使用者回報 | D125: 乳清蛋白粉 40g + 豆漿 1 杯 | E125: 43 | F125: 304 | G125: 估算沿用既有設定：乳清蛋白粉 40g 約蛋白質 30g、碳水 4g、160 kcal；豆漿約蛋白質 13g、碳水 13g、144 kcal。 | H125: 17
A126: 46248 | B126: 晚餐 | C126: 一般烤肉份量估算 | D126: 烤肉：旗魚黑輪 1 串 + 雞腿肉 3 串 + 雞胗 1 串 + 豆皮 1 份 + 牛肉串 2 串 | E126: 80 | F126: 820 | G126: 估算僅依使用者提供的品項與串數，不另計未提及的白飯、飲料或額外配菜。以一般夜市／烤肉攤常見單串份量估算：約旗魚黑輪 120 kcal、蛋白質 6 g、碳水 12 g；雞腿肉 3 串合計 270 kcal、蛋白質 30 g、碳水 6 g；雞胗 1 串 60 kcal、蛋白質 10 g；豆皮 1 份 150 kcal、蛋白質 10 g、碳水 8 g；牛肉串 2 串合計 220 kcal、蛋白質 24 g、碳水 4 g。總計約蛋白質 80 g、碳水 30 g、820 kcal。實際串重、油脂與醬料會造成誤差。 | H126: 30
A127: 46248 | B127: 晚餐 | C127: 估算 | D127: 乳清蛋白粉 40g | E127: 32 | F127: 160 | G127: 未提供品牌與營養標示；以一般乳清蛋白粉每 40 g 約蛋白質 32 g、碳水 4 g、160 kcal 估算。 | H127: 4
A128: 46248 | B128: 晚餐 | C128: 使用者回報 | D128: 豆漿 | G128: 品牌、容量與營養標示未提供；依規則不猜份量，蛋白質、碳水與熱量暫留空白待補。
A129: 46248 | B129: 午餐 | C129: 使用者回報 | D129: 未進食 | G129: 使用者以『其他都沒有』回覆當晚剩餘缺漏，依上下文記為午餐未進食。
A130: 46249 | B130: 早餐 | C130: 使用者回報 | D130: 乳清蛋白粉 40g + 豆漿半杯 | E130: 36.5 | F130: 232 | G130: 估算沿用既有設定：乳清蛋白粉 40g 約蛋白質 30g、碳水 4g、160 kcal；豆漿半杯按既有一杯設定的一半估算，約蛋白質 6.5g、碳水 6.5g、72 kcal。 | H130: 10.5
A131: 46249 | B131: 午餐 | C131: 一般份量估算 | D131: 雞腿肉套餐 + 花椰菜 1 份 | E131: 45 | F131: 720 | G131: 估算：未提供店家、雞腿肉重量、主食份量與套餐配菜細節；先以一般雞腿肉套餐加一份花椰菜估算約蛋白質 45 g、碳水 70 g、720 kcal。不另計未提及飲料與額外醬料。 | H131: 70
A132: 46249 | B132: 晚餐 | C132: 沿用既有估算設定 | D132: 乳清蛋白粉 60g + 豆漿 1 杯 | E132: 58 | F132: 384 | G132: 沿用既有 60 g 乳清 + 1 杯豆漿估算設定：約蛋白質 58 g、碳水 19 g、384 kcal；本次未提供品牌與容量。 | H132: 19
A133: 46250 | B133: 早餐 | C133: 使用者回報 | D133: 豆漿 1 杯 + 乳清蛋白粉 40g + 地瓜 | E133: 45 | F133: 429 | G133: 估算沿用既有設定：豆漿約蛋白質 13g、碳水 13g、144 kcal；乳清蛋白粉 40g 約蛋白質 30g、碳水 4g、160 kcal；地瓜約蛋白質 2g、碳水 35g、125 kcal。 | H133: 52
A134: 46250 | B134: 晚餐 | C134: 使用者回報 | D134: 三元酒樓：烤鴨 + 佛跳牆 + 脆皮雞 | E134: 90 | F134: 1400 | G134: 未提供各道實際食用份量，按一般中式聚餐個人食用量做透明估算：約蛋白質 90g、碳水 45g、1400 kcal。烤鴨與脆皮雞的皮脂、佛跳牆配料與湯汁會使熱量誤差較大，實際可上下浮動約 300–500 kcal；若補充吃了幾塊鴨、雞、是否有餅皮或飯，可再修正。 | H134: 45
A135: 46250 | B135: 午餐 | C135: 使用者回報 | D135: 未進食 | G135: 使用者回覆其他沒有，依當晚剩餘缺漏記為午餐未進食。
A136: 46251 | B136: 早餐 | C136: 使用者回報＋乳清一般估算 | D136: 地瓜 + 乳清蛋白粉 40g + 豆漿 1 杯 | E136: 32 | F136: 160 | G136: 乳清 40g 先以一般估算約蛋白質 32g、碳水 4g、160 kcal；地瓜重量與豆漿品牌／容量未提供，因此不猜其營養數值，早餐實際總量高於本列已填數值。 | H136: 4
A137: 46251 | B137: 午餐 | C137: 使用者回報＋乳清一般估算 | D137: 乳清蛋白粉 40g + 豆漿 1 杯 | E137: 32 | F137: 160 | G137: 乳清 40g 先以一般估算約蛋白質 32g、碳水 4g、160 kcal；豆漿品牌／容量未提供，因此不猜其營養數值，午餐實際總量高於本列已填數值。 | H137: 4
A138: 46251 | B138: 晚餐 | C138: 使用者回報 | D138: 三顧茅廬：豬肉片、牛肉片、高麗菜、凍豆腐、大豆干、蛋、冬粉、三角油豆腐、經典乾拌麵(F) | G138: 各配料與麵體實際重量／份量未提供；依規則不猜份量，因此蛋白質、碳水與熱量暫留空白。
A139: 46252 | B139: 早餐 | C139: 使用者回報 | D139: 乳清蛋白粉 40g + 豆漿 1 杯 + 地瓜 | E139: 45 | F139: 429 | G139: 估算沿用既有設定：乳清蛋白粉 40g 約蛋白質 30g、碳水 4g、160 kcal；豆漿約蛋白質 13g、碳水 13g、144 kcal；地瓜約蛋白質 2g、碳水 35g、125 kcal。 | H139: 52
A140: 46252 | B140: 午餐 | C140: 使用者回報；公開菜單確認套餐含主餐、小菜與味噌豆腐湯 | D140: 三商鮮五丼 麻婆魚排套餐 | E140: 30 | F140: 850 | G140: 透明估算：約蛋白質 30g、碳水 105g、850 kcal。公開菜單顯示麻婆魚排為麻婆醬搭配厚切魚排，套餐另含小菜與味噌豆腐湯；店家未提供完整營養標示，實際熱量會受飯量、炸魚排吸油與麻婆醬份量影響，估計誤差約 ±150–200 kcal。 | H140: 105
A141: 46252 | B141: 晚餐 | C141: 使用者回報＋既有乳清/豆漿設定＋公開營養標示 | D141: 乳清蛋白粉 60g + 豆漿 1 瓶 + 全家 芝麻香鬆飯糰 | E141: 63.6 | F141: 613 | G141: 估算沿用既有設定：乳清蛋白粉 60g 約蛋白質 45g、碳水 6g、240 kcal；豆漿 1 瓶先沿用既有一份設定約蛋白質 13g、碳水 13g、144 kcal。全家芝麻香鬆飯糰公開營養標示每份 104g：蛋白質 5.6g、碳水 38.1g、229 kcal。合計約蛋白質 63.6g、碳水 57.1g、613 kcal；若本次豆漿品牌/容量與既有設定不同，可再修正。 | H141: 57.1
A142: 46253 | B142: 早餐 | C142: 使用者回報 | D142: 雞胸肉 1 份 + 地瓜 1 份 + 豆漿 1 杯 + 乳清蛋白粉 40g | E142: 75 | F142: 589 | G142: 估算沿用既有設定：雞胸肉 1 份約蛋白質 30g、160 kcal；地瓜 1 份約蛋白質 2g、碳水 35g、125 kcal；豆漿 1 杯約蛋白質 13g、碳水 13g、144 kcal；乳清蛋白粉 40g 約蛋白質 30g、碳水 4g、160 kcal。 | H142: 52
A143: 46253 | B143: 午餐 | C143: 使用者回報 | D143: 豆漿 1 杯 | E143: 13 | F143: 144 | G143: 估算沿用既有設定：豆漿 1 杯約蛋白質 13g、碳水 13g、144 kcal。 | H143: 13
A144: 46253 | B144: 晚餐 | C144: 使用者回報 | D144: 韭菜水餃 10 顆 | E144: 16 | F144: 520 | G144: 修正估算：先前蛋白質 22g 偏高。參考台灣韭菜水餃公開營養標示，多數約每 100g 蛋白質 8–9g；在未提供品牌與單顆重量下，10 顆一般大小先改估蛋白質約 16g。熱量與碳水暫維持原估算，若補充品牌/單顆重量可再精修。 | H144: 65
A145: 46253 | B145: 晚餐 | C145: 使用者回報＋一般中型香蕉估算 | D145: 香蕉 1 根 | E145: 1.3 | F145: 105 | G145: 未提供香蕉重量，先以一般中型香蕉透明估算：約蛋白質 1.3g、碳水 27g、105 kcal；實際依大小會有差異。 | H145: 27
A146: 46253 | B146: 晚餐 | C146: 使用者回報＋沿用既有估算設定 | D146: 豆漿 1 杯 + 乳清蛋白粉 40g | E146: 43 | F146: 304 | G146: 沿用既有設定：乳清蛋白粉 40g 約蛋白質 30g、碳水 4g、160 kcal；豆漿 1 杯約蛋白質 13g、碳水 13g、144 kcal。作為同日晚餐追加紀錄，不覆蓋既有水餃與香蕉。 | H146: 17
A147: 46254 | B147: 晚餐 | C147: 使用者回報 | D147: 厚野雞排：炸雞排 + 炸魷魚 + 香蕉 1 根 + 乳清蛋白粉 40g + 豆漿 1 杯 | E147: 99 | F147: 1289 | G147: 透明估算：炸雞排與炸魷魚未提供實際重量，先沿用一般台式炸物份量估算，兩者合計約蛋白質 54g、碳水 70g、880 kcal；香蕉 1 根約蛋白質 2g、碳水 27g、105 kcal；乳清蛋白粉 40g + 豆漿 1 杯沿用既有設定約蛋白質 43g、碳水 17g、304 kcal。炸物實際熱量受大小、裹粉與吸油量影響大，整餐估算誤差可達約 ±200–300 kcal。 | H147: 114
A148: 46254 | B148: 早餐 | C148: 使用者回報＋沿用既有估算設定 | D148: 地瓜 + 雞胸肉 + 豆漿 1 杯 + 乳清蛋白粉 40g | E148: 75 | F148: 589 | G148: 沿用既有相同組合設定：雞胸肉約蛋白質 30g、160 kcal；乳清蛋白粉 40g 約蛋白質 30g、碳水 4g、160 kcal；豆漿 1 杯約蛋白質 13g、碳水 13g、144 kcal；地瓜約蛋白質 2g、碳水 35g、125 kcal。 | H148: 52
A149: 46254 | B149: 午餐 | C149: 使用者回報 | D149: 未進食 | G149: 使用者回覆其他都沒有，依當晚剩餘缺漏記為午餐未進食。
A150: 46255 | B150: 早餐 | C150: 使用者回報 | D150: 地瓜 1 份 + 雞胸肉 1 份 | E150: 32 | F150: 285 | G150: 估算沿用既有設定：地瓜 1 份約蛋白質 2g、碳水 35g、125 kcal；雞胸肉 1 份約蛋白質 30g、160 kcal。 | H150: 35
A151: 46255 | B151: 午餐 | C151: 使用者回報 | D151: 蚵仔滷肉飯 1 碗 | E151: 22 | F151: 680 | G151: 透明估算：未提供店家與實際份量，先按一般一碗蚵仔滷肉飯估算約蛋白質 22g、碳水 85g、680 kcal。主要誤差來自白飯份量、滷肉肥瘦與醬汁；若補充照片或店家可再修正。 | H151: 85
A152: 46255 | B152: 午餐 | C152: 使用者回報 | D152: 香蕉 1 根 | E152: 1.3 | F152: 105 | G152: 估算：一般中型香蕉 1 根約蛋白質 1.3g、碳水 27g、105 kcal。 | H152: 27
A153: 46255 | B153: 晚餐 | C153: 使用者更正 | D153: 滷肉飯 1 碗 + 肝連 1 份 + 豬肝 1 份 | E153: 58 | F153: 750 | G153: 使用者更正：原先誤記為嘴邊肉，實際為豬肝。未提供實際份量，先按一般小吃店常見個人份量透明估算：滷肉飯 1 碗 + 肝連 1 份 + 豬肝 1 份，約蛋白質 58g、碳水 65g、750 kcal；實際飯量、滷肉肥瘦與肉類份量會造成明顯誤差。 | H153: 65
A154: 46256 | B154: 早餐 | C154: 使用者回報；7-ELEVEN 官方現售雙蔬鮪魚飯糰熱量與公開營養標示 | D154: 乳清蛋白粉 40g + 地瓜 1 份 + 7-ELEVEN 鮮蔬鮪魚御飯糰 1 個 | E154: 37 | F154: 506 | G154: 乳清 40g 沿用既有設定：約蛋白質 30g、碳水 4g、160 kcal；地瓜 1 份沿用既有設定：約蛋白質 2g、碳水 35g、125 kcal。使用者稱『711鮮蔬鮪魚御飯糰』，按目前 7-ELEVEN 官網對應的雙蔬鮪魚飯糰記錄：官方熱量 221 kcal；公開營養標示約蛋白質 5g、碳水 38g。合計約蛋白質 37g、碳水 77g、506 kcal。 | H154: 77
A155: 46256 | B155: 晚餐 | C155: 使用者回報＋點餐畫面確認＋一般份量透明估算 | D155: 竹間火鍋：美國低脂牛肉 + 潮鯛魚片鍋套餐（柴魚昆布湯）+ 雞蛋 3 顆 + 蝦滑丸子 4 顆 + 高麗菜 1 份 | E155: 80 | F155: 850 | G155: 圖片可確認套餐為『美國低脂牛肉+潮鯛魚片鍋套餐』，湯底為柴魚昆布湯；使用者另回報雞蛋 3 顆、蝦滑丸子 4 顆、高麗菜 1 份。未提供牛肉、魚片、蝦滑與高麗菜實際重量，亦未提及飯、麵、醬料或其他配菜，因此不另計未提及品項。先依一般火鍋份量透明估算整餐約蛋白質 80g、碳水 25g、850 kcal，實際會受肉盤重量、蝦滑配方與湯汁攝取量影響。 | H155: 25
A156: 46256 | B156: 晚餐 | C156: 使用者回報＋一般火鍋份量估算 | D156: 金針菇 2 份 + 火鍋料大小芋頭 1 顆 + 小條天婦羅 2 條 | E156: 7 | F156: 130 | G156: 使用者未提供實際重量；以一般火鍋常見小份量透明估算。未辨識的綠色蔬菜依使用者指示不計入。 | H156: 22
A157: 46256 | B157: 午餐 | C157: 使用者回報 | D157: 未進食 | G157: 使用者回覆其他都沒有，依當晚剩餘缺漏記為午餐未進食。
A158: 46257 | B158: 早餐 | C158: 使用者回報 | D158: 香蕉 1 根 | E158: 1.3 | F158: 105 | G158: 透明估算：按一般中型香蕉 1 根估算，約蛋白質 1.3g、碳水 27g、105 kcal；實際大小會造成差異。 | H158: 27
A159: 46257 | B159: 午餐 | C159: 使用者回報 | D159: 牛肉麵（麵吃一半） | E159: 30 | F159: 560 | G159: 透明估算：未提供店家、牛肉份量、麵量與湯底油脂；按一般牛肉麵、麵只吃約一半估算約蛋白質 30g、碳水 45g、560 kcal。牛肉塊數、是否喝湯與湯底油脂會使實際熱量有明顯差異，估計誤差約 ±150 kcal。 | H159: 45
A160: 46257 | B160: 下午 | C160: 使用者回報 | D160: 乳清蛋白粉 60g | E160: 45 | F160: 240 | G160: 估算沿用既有設定：乳清蛋白粉 60g 約蛋白質 45g、碳水 6g、240 kcal。 | H160: 6
A161: 46257 | B161: 晚餐 | C161: 使用者回報 | D161: 腿庫飯（半肥半瘦） | E161: 28 | F161: 780 | G161: 透明估算：未提供店家、飯量、腿庫肉實際重量與配菜；按一般小吃店腿庫飯、肉為半肥半瘦估約蛋白質 28g、碳水 80g、780 kcal。肥肉比例、滷汁與白飯份量會造成明顯誤差，估計約 ±150–200 kcal。 | H161: 80
A162: 46257 | B162: 晚餐 | C162: 使用者回報 | D162: 香蕉 1 根 | E162: 1.3 | F162: 105 | G162: 透明估算：按一般中型香蕉 1 根估算，約蛋白質 1.3g、碳水 27g、105 kcal；實際大小會造成差異。 | H162: 27
A163: 46257 | B163: 晚餐 | C163: 使用者回報 | D163: 乳清蛋白粉 60g | E163: 45 | F163: 240 | G163: 估算沿用既有設定：乳清蛋白粉 60g 約蛋白質 45g、碳水 6g、240 kcal。 | H163: 6
A164: 46258 | B164: 早餐 | C164: 使用者回報 | D164: 地瓜 1 份 + 雞胸肉 1 份 + 乳清蛋白粉 60g | E164: 77 | F164: 525 | G164: 估算沿用既有設定：地瓜 1 份約蛋白質 2g、碳水 35g、125 kcal；雞胸肉 1 份約蛋白質 30g、160 kcal；乳清蛋白粉 60g 約蛋白質 45g、碳水 6g、240 kcal。 | H164: 41
A165: 46258 | B165: 晚餐 | C165: 使用者回報＋包裝熱量 | D165: 雞胸肉 1 份 + 乳清蛋白粉 40g + 7-ELEVEN 潮粵坊京醬鴨絲飯糰 1 個 | E165: 66 | F165: 652 | G165: 使用者補充京醬鴨絲飯糰包裝熱量為 332 kcal。雞胸肉 1 份沿用既有設定約蛋白質 30g、160 kcal；乳清蛋白粉 40g 約蛋白質 30g、碳水 4g、160 kcal；飯糰熱量改採使用者提供 332 kcal。飯糰蛋白質與碳水因未提供完整營養標示，暫沿用原估算約蛋白質 6g、碳水 40g。整餐約蛋白質 66g、碳水 44g、652 kcal。 | H165: 44
A166: 46259 | B166: 晚餐 | C166: 使用者回報 | D166: 樂晴牛排館 牛雞雙拼 | E166: 88 | F166: 1450 | G166: 使用者補充：鐵板麵有吃完，另有酥皮濃湯。透明估算修正為牛排＋雞排雙主餐、完整鐵板麵與醬汁、酥皮濃湯合計約蛋白質 88g、碳水 105g、1450 kcal；實際肉排大小、雞排油脂、麵量、醬汁與酥皮濃湯配方會造成明顯差異，估計誤差約 ±250–350 kcal。 | H166: 105
A167: 46259 | B167: 晚餐 | C167: 使用者回報 | D167: 香蕉 1 根 | E167: 1.3 | F167: 105 | G167: 透明估算：按一般中型香蕉 1 根估算，約蛋白質 1.3g、碳水 27g、105 kcal；實際大小會造成差異。 | H167: 27
A168: 46259 | B168: 早餐 | C168: 使用者更正 | D168: 地瓜 1 份 + 雞胸肉 1 份 + 乳清蛋白粉 40g | E168: 62 | F168: 445 | G168: 使用者更正：早餐有喝乳清蛋白粉 40g。估算沿用既有設定：地瓜 1 份約蛋白質 2g、碳水 35g、125 kcal；雞胸肉 1 份約蛋白質 30g、160 kcal；乳清蛋白粉 40g 約蛋白質 30g、碳水 4g、160 kcal。 | H168: 39
A169: 46260 | B169: 晚餐 | C169: 使用者回報＋吃剩照片估算 | D169: 牛肉麵 1 碗 | E169: 38 | F169: 650 | G169: 使用者補充牛肉麵的麵沒有吃完。依吃剩照片觀察，牛肉大致已吃完，但約仍剩 40–50% 麵量與不少湯。由原先完整一碗估算 850 kcal、蛋白質 42g、碳水 95g，下修為實際攝取約蛋白質 38g、碳水 60g、650 kcal。實際剩餘麵量與湯汁攝取仍有誤差，估計約 ±120–180 kcal。 | H169: 60
... A172: 46260 | B172: 早餐 | C172: 使用者回報 | D172: 雞胸肉 1 份 + 地瓜 1 份 | E172: 32 | F172: 285 | G172: 估算沿用既有設定：雞胸肉 1 份約蛋白質 30g、160 kcal；地瓜 1 份約蛋白質 2g、碳水 35g、125 kcal。 | H172: 35
A173: 46260 | B173: 午餐 | C173: 使用者回報 | D173: 未進食 | G173: 使用者明確回報午餐沒有吃。
A174: 46261 | B174: 早餐 | C174: 使用者回報 | D174: 雞胸肉 1 份 + 7-ELEVEN 海鹽水煮蛋 2 顆 + 地瓜 1 份 | E174: 42.8 | F174: 391 | G174: 估算沿用既有設定：雞胸肉 1 份約蛋白質 30g、160 kcal；地瓜 1 份約蛋白質 2g、碳水 35g、125 kcal；7-ELEVEN 海鹽水煮蛋 2 顆沿用先前雞蛋估算，每顆約蛋白質 5.4g、碳水 1.4g、53 kcal。 | H174: 37.8
A175: 46261 | B175: 晚餐 | C175: 使用者回報＋照片估算 | D175: 牛腩咖哩飯（牛腩約 7 塊） | E175: 35 | F175: 1050 | G175: 依照片與使用者回報估算：大盤白飯、咖哩醬、馬鈴薯/紅蘿蔔與牛腩約 7 塊。白飯份量看起來偏大，約 2 碗上下；牛腩約 7 塊。整份先估蛋白質約 35g、碳水約 125g、1050 kcal。實際飯量、牛腩肥瘦與咖哩油脂可能使熱量誤差約 ±200 kcal。 | H175: 125
A176: 46262 | B176: 早餐 | C176: 使用者回報 | D176: 乳清蛋白粉 40g + 雞胸肉 1 份 + 地瓜 1 份 + 肌酸 5g | E176: 62 | F176: 445 | G176: 估算沿用既有設定：乳清蛋白粉 40g 約蛋白質 30g、碳水 4g、160 kcal；雞胸肉 1 份約蛋白質 30g、160 kcal；地瓜 1 份約蛋白質 2g、碳水 35g、125 kcal；肌酸 5g 不另計蛋白質、碳水或熱量。 | H176: 39
A177: 46262 | B177: 晚餐 | C177: 使用者回報＋7-ELEVEN 官方熱量＋既有雞蛋估算 | D177: 7-ELEVEN 林聰明雞肉飯飯糰 1 個 + 茶葉蛋 2 顆 | E177: 16.8 | F177: 332 | G177: 7-ELEVEN 官方目前列林聰明-雞肉飯飯糰每個 226 kcal；完整蛋白質與碳水未公開，先以一般同尺寸飯糰約蛋白質 6g、碳水 38g 估算。茶葉蛋 2 顆沿用既有 7-ELEVEN 雞蛋估算，每顆約蛋白質 5.4g、碳水 1.4g、53 kcal。合計約蛋白質 16.8g、碳水 40.8g、332 kcal；若有包裝營養標示可再修正。 | H177: 40.8
A178: 46262 | B178: 晚餐 | C178: 使用者回報＋既有乳清估算 | D178: 乳清蛋白粉 80g | E178: 60 | F178: 320 | G178: 估算沿用既有設定：乳清蛋白粉 80g 約蛋白質 60g、碳水 8g、320 kcal。 | H178: 8
A179: 46262 | B179: 午餐 | C179: 使用者回報 | D179: 未進食 | E179: 0 | F179: 0 | G179: 使用者明確回報今天午餐未進食。 | H179: 0
A180: 46263 | B180: 早餐 | C180: 使用者回報＋既有乳清/地瓜/香蕉估算 | D180: 乳清蛋白粉 40g + 雞胸肉 1 份 + 地瓜 1 份 + 香蕉 2 根 | E180: 56.6 | F180: 615 | G180: 使用者明確回報雞胸肉蛋白質 22g。估算：乳清蛋白粉 40g 約蛋白質 30g、碳水 4g、160 kcal；雞胸肉本次採蛋白質 22g，熱量先以一般低脂雞胸相近份量估約 120 kcal、碳水 0g；地瓜 1 份約蛋白質 2g、碳水 35g、125 kcal；香蕉 2 根按一般中型香蕉每根約蛋白質 1.3g、碳水 27g、105 kcal。合計約蛋白質 56.6g、碳水 93g、615 kcal。若雞胸包裝有熱量標示可再修正。 | H180: 93
A181: 46263 | B181: 晚餐 | C181: 使用者回報＋公開菜單確認品項＋一般椒麻雞飯營養估算 | D181: 梁社漢 椒麻雞飯 1 份 | E181: 50 | F181: 900 | G181: 公開菜單可確認梁社漢椒麻雞飯為去骨雞腿、椒麻醬、高麗菜絲與白飯；店家未公開完整營養標示。參考同類椒麻雞腿飯公開營養資料與一般便當份量，先估約蛋白質 50g、碳水 100g、900 kcal；主要誤差來自雞腿油脂、炸粉/吸油、白飯份量與椒麻醬，估計誤差約 ±150–200 kcal。 | H181: 100
A182: 46263 | B182: 午餐 | C182: 使用者回報 | D182: 未進食 | E182: 0 | F182: 0 | G182: 使用者明確回報今天午餐未進食。 | H182: 0
A183: 46263 | B183: 晚餐 | C183: 使用者回報＋既有乳清估算 | D183: 乳清蛋白粉 40g | E183: 30 | F183: 160 | G183: 估算沿用既有設定：乳清蛋白粉 40g 約蛋白質 30g、碳水 4g、160 kcal。 | H183: 4
A184: 46264 | B184: 早餐 | C184: 使用者回報＋既有乳清/雞胸/地瓜估算 | D184: 乳清蛋白粉 40g + 雞胸肉 1 份 + 地瓜 1 份 | E184: 62 | F184: 445 | G184: 估算沿用既有設定：乳清蛋白粉 40g 約蛋白質 30g、碳水 4g、160 kcal；雞胸肉 1 份約蛋白質 30g、160 kcal；地瓜 1 份約蛋白質 2g、碳水 35g、125 kcal。 | H184: 39
A185: 46264 | B185: 晚餐 | C185: 使用者回報＋一般份量估算 | D185: 美式漢堡 1 個 + 雞塊 6 塊 | E185: 42 | F185: 850 | G185: 未提供店家、漢堡肉排大小、起司/醬料與雞塊品牌，先按一般美式牛肉漢堡 1 個加雞塊 6 塊透明估算：約蛋白質 42g、碳水 65g、850 kcal。實際熱量受肉排大小、起司、醬料、麵包與炸雞塊吸油量影響，估計誤差約 ±200 kcal；若補充店家或照片可再修正。 | H185: 65
...

Sheet 營養設定
A1: 營養設定
A2: 以下為你指定的固定蛋白質估算；未設定食物保持空白，不自行推估。
A4: 食物 | B4: 蛋白質（g） | C4: 熱量（kcal） | D4: 套用說明
A5: 豆漿 | B5: 13 | C5: 144 | D5: 每瓶／份
A6: 地瓜 | B6: 2 | D6: 每份
A7: 雞胸肉 | B7: 25 | D7: 每份
A8: 牛排 | B8: 50 | D8: 每份
A9: 雞腿排 | B9: 45 | D9: 每份
A10: 雞排（視為雞腿排） | B10: 45 | D10: 用於舊紀錄；可依實際品項更正
A11: 大麥克 | B11: 26 | D11: 每份
A13: 既有飲食：已設定蛋白質每日小計
A14: 日期 | B14: 蛋白質（g） | C14: 說明
A15: 46237 | B15: =SUMIF('飲食紀錄'!$A$5:$A$94,A15,'飲食紀錄'!$E$5:$E$94) | C15: 僅合計已設定食物
A16: 46238 | B16: =SUMIF('飲食紀錄'!$A$5:$A$94,A16,'飲食紀錄'!$E$5:$E$94) | C16: 僅合計已設定食物
A17: 46239 | B17: =SUMIF('飲食紀錄'!$A$5:$A$94,A17,'飲食紀錄'!$E$5:$E$94) | C17: 僅合計已設定食物
A18: 46240 | B18: =SUMIF('飲食紀錄'!$A$5:$A$94,A18,'飲食紀錄'!$E$5:$E$94) | C18: 僅合計已設定食物
A19: 46241 | B19: 102 | C19: 僅合計已設定食物
A20: 46242 | B20: 172 | C20: 早餐 32g＋午餐 58g＋晚餐 82g；蛋白質合計

Sheet 營養來源
A1: 營養估算來源
A2: 黃色為依餐點或通用份量的估算；綠色為官方、包裝標示或使用者提供數字。
A4: 日期／餐別 | B4: 資料類型 | C4: 來源 | D4: 用途
A5: 2026-08-03 早餐 | B5: 通用估算 | C5: https://meals.ntu.edu.tw/CampusDining/kcal/breakfast | D5: 培根蛋三明治熱量基準；雞塊按常見一份估算
A6: 2026-08-03 晚餐 | B6: 餐廳菜單＋通用估算 | C6: https://www.ubereats.com/tw/store/%E6%A8%82%E6%99%B4%E7%89%9B%E6%8E%92%E9%A4%A8/ilGt4LRHXgmSOVWjMT71Eg | D6: 樂晴牛排館品項描述；雙排餐份量估算
A7: 2026-08-04 早餐 | B7: 通用估算 | C7: https://www.7-11.com.tw/freshfoods/4_snacks/index.aspx | D7: 7-ELEVEN 類似品項與一般份量
A8: 2026-08-04 午餐 | B8: 官方／公開營養資料 | C8: https://www.mcdonalds.com/tw/zh-tw/sustainability/good-food/nutrition.html | D8: 大麥克、中薯、小杯玉米湯、無糖可樂
A9: 2026-08-04 晚餐 | B9: 使用者提供 | C9: 使用者回報 | D9: 850 kcal、蛋白質 65 g
A10: 2026-08-05 早餐／晚餐 | B10: 包裝標示／通用估算 | C10: 包裝照片；https://www.fda.gov.tw/tc/site.aspx?r=1003484775&sid=271 | D10: 飯糰採包裝標示；鐵板燒採通用份量估算
A11: 2026-08-06 早餐 | B11: 通用估算 | C11: https://www.fda.gov.tw/tc/site.aspx?r=1003484775&sid=271 | D11: 全家豆漿、地瓜、雞胸採一般份量估算
A12: 2026-08-06 午餐 | B12: 通用估算 | C12: 使用者回報，未提供品牌或標示 | D12: 乳清粉 40g 暫以蛋白質 30g、160 kcal 計
A13: 2026-08-06 晚餐 | B13: 通用估算 | C13: https://health.tvbs.com.tw/nutrition/351544；https://www.mos.com.tw/menu/Detail.aspx?id=M001236 | D13: 炸雞排、炸杏鮑菇與炸魷魚的公開熱量資料；蛋白質依一般份量估算
A14: 2026-08-07 三餐 | B14: 通用估算 | C14: https://www.fda.gov.tw/tc/site.aspx?r=1003484775&sid=271 | D14: 早餐、乳清與火鍋肉片依既有設定或一般份量估算
A15: 2026-08-08 早餐／晚餐 | B15: 使用者回報＋既有設定 | C15: 使用者回報 | D15: 雞胸肉 30g 蛋白質；乳清 60g 粉與豆漿依既有比例估算
... A17: 2026-08-08 晚餐 | B17: 好食多涮涮鍋資訊＋使用者回報 | C17: https://www.fonfood.com/store/416083 | D17: 昆布鍋與肉盤份量參考；12 盎司、鮑魚與白飯由使用者回報。無公開營養標示，故熱量與蛋白質採估算。

Sheet 有氧紀錄
A1: 日期 | B1: 有氧類型 | C1: 段次 | D1: 時間（分鐘） | E1: 坡度（%） | F1: 速度（km/h） | G1: 距離（km） | H1: 備註
A2: 46262 | B2: 跑步機爬坡 | C2: 1 | D2: 20 | E2: 12 | F2: 4.1 | H2: 使用者回報：爬坡坡度 12、速度 4.1 km/h、20 分鐘；獨立記錄，不併入散步分鐘。
A3: 46267 | B3: 跑步機爬坡 | C3: 1 | D3: 30 | E3: 12 | F3: 4.1 | H3: 使用者回報：爬坡坡度 12、速度 4.1 km/h、30 分鐘；獨立記錄，不併入散步分鐘。
A4: 46270 | B4: 跑步機有氧 | C4: 1 | D4: 20 | E4: 1 | F4: 3.3 | H4: 重訓後跑步機有氧；心率約142 bpm。與日常散步分開記錄，也不與12%高坡度爬坡混為同一強度。

Sheet 動作基準
A1: 動作 | B1: 建議下次重量（kg） | C1: 建議目標次數 | D1: 建議DBR | E1: 最近訓練日期 | F1: 最近使用重量（kg） | G1: 最近次數 | H1: 最近DBR | I1: 最近訓練摘要 | J1: 狀態／注意 | K1: 建議依據
A2: 上斜胸推 | C2: 10–15（特殊動作可依既有表現調整） | D2: 1–3；最後一組可視情況 DBR0 | E2: 2026-09-11 | F2: 20 | G2: 12 | H2: 1 | I2: 25kg×15/DBR1；25kg×13/DBR1；25kg×9/DBR0；20kg×12/DBR1 | J2: 疼痛／不適：暫不自動推薦重量 | K2: 最近一次訓練備註出現疼痛／不適；保留歷史重量，但下次先確認無痛，不依重量基準直接加載。
A3: 保加利亞分腿蹲 | B3: 10 | C3: 10–15（特殊動作可依既有表現調整） | D3: 1–3；最後一組可視情況 DBR0 | E3: 2026-09-11 | F3: 10 | G3: 10 | H3: 1 | I3: 左10kg×15/DBR2；左10kg×15/DBR2；左10kg×12/DBR2；左10kg×12/DBR2；左10kg×13/DBR2；右10kg×10/DBR2；左10kg×12/DBR1；右10kg×10/DBR1 | J3: 正常 | K3: 最近一次訓練中 10 kg 有 8 組落在約 8–20 下、DBR1–3；以可重複的工作組表現優先，不直接選最高重量。
A4: 划船 | B4: 26.5 | C4: 10–15（特殊動作可依既有表現調整） | D4: 1–3；最後一組可視情況 DBR0 | E4: 2026-09-07 | F4: 30 | G4: 13 | H4: 0 | I4: 26.5kg×15/DBR4；26.5kg×15/DBR2；30kg×13/DBR2；30kg×13/DBR0；30kg×13/DBR0 | J4: 正常 | K4: 最近一次訓練中 26.5 kg 有 1 組落在約 8–20 下、DBR1–3；以可重複的工作組表現優先，不直接選最高重量。
A5: 反向飛鳥 | B5: 15 | C5: 10–15（特殊動作可依既有表現調整） | D5: 1–3；最後一組可視情況 DBR0 | E5: 2026-09-11 | F5: 15 | G5: 11 | H5: 1 | I5: 15kg×15/DBR3；15kg×15/DBR1；15kg×13/DBR1；15kg×13/DBR1；15kg×11/DBR1 | J5: 正常 | K5: 最近一次訓練中 15 kg 有 5 組落在約 8–20 下、DBR1–3；以可重複的工作組表現優先，不直接選最高重量。
A6: 啞鈴側平舉 | B6: 10 | C6: 10–15（特殊動作可依既有表現調整） | D6: 1–3；最後一組可視情況 DBR0 | E6: 2026-09-07 | F6: 10 | G6: 15 | H6: 0 | I6: 10kg×15/DBR1；10kg×13/DBR1；10kg×14/DBR1；10kg×15/DBR0 | J6: 正常 | K6: 最近一次訓練中 10 kg 有 3 組落在約 8–20 下、DBR1–3；以可重複的工作組表現優先，不直接選最高重量。
A7: 滑輪下拉 | B7: 37.5 | C7: 10–15（特殊動作可依既有表現調整） | D7: 1–3；最後一組可視情況 DBR0 | E7: 2026-09-11 | F7: 37.5 | G7: 8 | H7: 0 | I7: 37.5kg×13/DBR2；37.5kg×13/DBR2；37.5kg×11/DBR1；37.5kg×8/DBR0 | J7: 正常 | K7: 最近一次訓練中 37.5 kg 有 3 組落在約 8–20 下、DBR1–3；以可重複的工作組表現優先，不直接選最高重量。
A8: 睾丸繩下拉 | B8: 6.25 | C8: 10–15（特殊動作可依既有表現調整） | D8: 1–3；最後一組可視情況 DBR0 | E8: 2026-08-14 | F8: 6.25 | G8: 11 | H8: 0 | I8: 8.75kg×11/DBR0；8.75kg×10/DBR0；6.25kg×13/DBR0；6.25kg×13/DBR0；6.25kg×11/DBR0 | J8: 正常 | K8: 最近一次已知組多為力竭；下次採該次較低重量重新建立 DBR1–3 的工作組。
A9: 羅馬尼亞分腿蹲 | B9: 10 | C9: 10–15（特殊動作可依既有表現調整） | D9: 1–3；最後一組可視情況 DBR0 | E9: 2026-09-05 | F9: 10 | G9: 11 | H9: 1 | I9: 左10kg×15/DBR3；右10kg×15/DBR3；左10kg×15/DBR2；右10kg×15/DBR2；左10kg×15/DBR1；右10kg×11/DBR1；左10kg×11/DBR2；右10kg×11/DBR1 | J9: 正常 | K9: 最近一次訓練中 10 kg 有 8 組落在約 8–20 下、DBR1–3；以可重複的工作組表現優先，不直接選最高重量。
A10: 羅馬尼亞蹲 | B10: 5 | C10: 10–15（特殊動作可依既有表現調整） | D10: 1–3；最後一組可視情況 DBR0 | E10: 2026-08-12 | F10: 5 | G10: 14 | H10: 0 | I10: 左自重×15/DBR3；右自重×15/DBR3；左5kg×15/DBR2；右5kg×8/DBR0；左5kg×14/DBR0；右5kg×14/DBR0；左5kg×14/DBR0；右5kg×14/DBR0 | J10: 正常 | K10: 最近一次訓練中 5 kg 有 1 組落在約 8–20 下、DBR1–3；以可重複的工作組表現優先，不直接選最高重量。
A11: 腿內收 | B11: 37.5 | C11: 10–15（特殊動作可依既有表現調整） | D11: 1–3；最後一組可視情況 DBR0 | E11: 2026-09-11 | F11: 37.5 | G11: 13 | H11: 0 | I11: 37.5kg×13/DBR2；37.5kg×13/DBR1；37.5kg×13/DBR1；37.5kg×13/DBR0 | J11: 正常 | K11: 最近一次訓練中 37.5 kg 有 3 組落在約 8–20 下、DBR1–3；以可重複的工作組表現優先，不直接選最高重量。
A12: 腿外展 | B12: 45 | C12: 10–15（特殊動作可依既有表現調整） | D12: 1–3；最後一組可視情況 DBR0 | E12: 2026-09-07 | F12: 45 | G12: 15 | H12: 2 | I12: 40.8kg×15/DBR4；48.75kg×15/DBR1；45kg×15/DBR1；45kg×12/DBR2；45kg×15/DBR2 | J12: 正常 | K12: 最近一次訓練中 45 kg 有 3 組落在約 8–20 下、DBR1–3；以可重複的工作組表現優先，不直接選最高重量。
A13: 腿後勾 | B13: 47 | C13: 10–15（特殊動作可依既有表現調整） | D13: 1–3；最後一組可視情況 DBR0 | E13: 2026-09-07 | F13: 47 | G13: 13 | H13: 0 | I13: 40kg×15/DBR3；47kg×15/DBR1；47kg×12/DBR1；47kg×13/DBR0 | J13: 正常 | K13: 最近一次訓練中 47 kg 有 2 組落在約 8–20 下、DBR1–3；以可重複的工作組表現優先，不直接選最高重量。
A14: 腿推舉 | B14: 40 | C14: 10–15（特殊動作可依既有表現調整） | D14: 1–3；最後一組可視情況 DBR0 | E14: 2026-08-04 | F14: 40 | G14: 16 | H14: 0 | I14: 40kg×16/DBR3；40kg×18/DBR2；40kg×16/DBR1；40kg×16/DBR0 | J14: 正常 | K14: 最近一次訓練中 40 kg 有 3 組落在約 8–20 下、DBR1–3；以可重複的工作組表現優先，不直接選最高重量。
A15: 臀推機 | C15: 10–15（特殊動作可依既有表現調整） | D15: 1–3；最後一組可視情況 DBR0 | E15: 2026-08-28 | F15: 20 | G15: 12 | H15: 2 | I15: 20kg×12/DBR3；20kg×12/DBR2；20kg×12/DBR2 | J15: 疼痛／不適：暫不自動推薦重量 | K15: 最近一次訓練備註出現疼痛／不適；保留歷史重量，但下次先確認無痛，不依重量基準直接加載。
A16: 蝴蝶機夾胸 | B16: 25 | C16: 10–15（特殊動作可依既有表現調整） | D16: 1–3；最後一組可視情況 DBR0 | E16: 2026-08-12 | F16: 20 | G16: 13 | H16: 0 | I16: 25kg×15/DBR3；20kg×15/DBR0；25kg×7/DBR0；20kg×13/DBR0 | J16: 正常 | K16: 最近一次訓練中 25 kg 有 1 組落在約 8–20 下、DBR1–3；以可重複的工作組表現優先，不直接選最高重量。
A17: 飛鳥夾胸 | B17: 20 | C17: 10–15（特殊動作可依既有表現調整） | D17: 1–3；最後一組可視情況 DBR0 | E17: 2026-08-28 | F17: 20 | G17: 10 | H17: 0 | I17: 20kg×15/DBR3；20kg×14/DBR2；20kg×12/DBR1；20kg×10/DBR0 | J17: 正常 | K17: 最近一次訓練中 20 kg 有 3 組落在約 8–20 下、DBR1–3；以可重複的工作組表現優先，不直接選最高重量。
